nestedaaddb/__init__.py
nestedaaddb/databricks_client.py
nestedaaddb/graph_client.py
nestedaaddb/logger_config.py
nestedaaddb/nested_groups.py
nestedaaddb-1.0.4.dist-info/METADATA
nestedaaddb-1.0.4.dist-info/WHEEL
nestedaaddb-1.0.4.dist-info/top_level.txt
nestedaaddb-1.0.4.dist-info/RECORD
