Metadata-Version: 2.2
Name: nestedaaddb
Version: 1.0.4
Summary: A package that allows to sync Nested AAD Group to DataBricks
Author: Abhishek Pratap Singh
Author-email: Abhishek Pratap Singh <sumoaps@outlook.com>
Keywords: Databricks,SCIM,nested AAD
Classifier: License :: OSI Approved :: MIT License
Classifier: Programming Language :: Python
Classifier: Programming Language :: Python :: 3
Requires-Python: >=3.6
Requires-Dist: azure-core
Requires-Dist: azure-identity
Requires-Dist: msgraph-core
Dynamic: author
Dynamic: requires-python
